setup.py
pycirculate/__init__.py
pycirculate/anova.py
pycirculate.egg-info/PKG-INFO
pycirculate.egg-info/SOURCES.txt
pycirculate.egg-info/dependency_links.txt
pycirculate.egg-info/top_level.txt