Metadata-Version: 1.1
Name: pycirculate
Version: 0.1.0a1
Summary: A Python wrapper for the Anova 2.
Home-page: https://github.com/erikcw/pycirculate
Author: Erik Wickstrom
Author-email: erik@erikwickstrom.com
License: MIT
Keywords: anova bluetooth bluepy sous vide
Platform: UNKNOWN
Classifier: Development Status :: 3 - Alpha
Classifier: Intended Audience :: Developers
Classifier: Topic :: System :: Hardware
Classifier: License :: OSI Approved :: MIT License
Classifier: Programming Language :: Python :: 2.7
Classifier: Operating System :: POSIX :: Linux
